openvisuspy/__init__.py
openvisuspy/backend.py
openvisuspy/backend_cpp.py
openvisuspy/backend_py.py
openvisuspy/bokeh_app.py
openvisuspy/canvas.py
openvisuspy/slice.py
openvisuspy/slices.py
openvisuspy/utils.py
openvisuspy/widgets.py
openvisuspy-2.1.2.dist-info/LICENSE
openvisuspy-2.1.2.dist-info/METADATA
openvisuspy-2.1.2.dist-info/WHEEL
openvisuspy-2.1.2.dist-info/top_level.txt
openvisuspy-2.1.2.dist-info/RECORD
