Metadata-Version: 2.1
Name: openvisuspy
Version: 2.1.2
Summary: openvisuspy
Author: OpenVisus developers
Project-URL: Homepage, https://github.com/sci-visus/openvisuspy
Project-URL: Bug Tracker, https://github.com/sci-visus/openvisuspy
Requires-Python: >=3.6
License-File: LICENSE
